odoo/addons/edi_state_oca/README.rst
odoo/addons/edi_state_oca/__init__.py
odoo/addons/edi_state_oca/__manifest__.py
odoo/addons/edi_state_oca/i18n/edi_state_oca.pot
odoo/addons/edi_state_oca/i18n/it.po
odoo/addons/edi_state_oca/models/__init__.py
odoo/addons/edi_state_oca/models/edi_exchange_type.py
odoo/addons/edi_state_oca/models/edi_state.py
odoo/addons/edi_state_oca/models/edi_state_consumer_mixin.py
odoo/addons/edi_state_oca/models/edi_state_workflow.py
odoo/addons/edi_state_oca/readme/CONFIGURE.md
odoo/addons/edi_state_oca/readme/CONTRIBUTORS.md
odoo/addons/edi_state_oca/readme/CREDITS.md
odoo/addons/edi_state_oca/readme/DESCRIPTION.md
odoo/addons/edi_state_oca/readme/ROADMAP.md
odoo/addons/edi_state_oca/readme/USAGE.md
odoo/addons/edi_state_oca/security/ir_model_access.xml
odoo/addons/edi_state_oca/static/description/icon.png
odoo/addons/edi_state_oca/static/description/index.html
odoo/addons/edi_state_oca/tests/__init__.py
odoo/addons/edi_state_oca/tests/fake_models.py
odoo/addons/edi_state_oca/tests/test_edi_state.py
odoo/addons/edi_state_oca/views/edi_exchange_type.xml
odoo/addons/edi_state_oca/views/edi_state.xml
odoo/addons/edi_state_oca/views/edi_state_workflow.xml
odoo/addons/edi_state_oca/views/menuitems.xml
odoo_addon_edi_state_oca-18.0.1.0.2.1.dist-info/METADATA
odoo_addon_edi_state_oca-18.0.1.0.2.1.dist-info/WHEEL
odoo_addon_edi_state_oca-18.0.1.0.2.1.dist-info/top_level.txt
odoo_addon_edi_state_oca-18.0.1.0.2.1.dist-info/RECORD
